st_img_picker/__init__.py
st_img_picker/frontend/.env
st_img_picker/frontend/.prettierrc
st_img_picker/frontend/build/asset-manifest.json
st_img_picker/frontend/build/index.html
st_img_picker/frontend/build/precache-manifest.6279650dbf82623ef7b06184c4ef3617.js
st_img_picker/frontend/build/service-worker.js
st_img_picker/frontend/build/static/js/2.e31505f2.chunk.js
st_img_picker/frontend/build/static/js/2.e31505f2.chunk.js.LICENSE.txt
st_img_picker/frontend/build/static/js/2.e31505f2.chunk.js.map
st_img_picker/frontend/build/static/js/main.52e540fe.chunk.js
st_img_picker/frontend/build/static/js/main.52e540fe.chunk.js.map
st_img_picker/frontend/build/static/js/runtime-main.fce4c018.js
st_img_picker/frontend/build/static/js/runtime-main.fce4c018.js.map
st_img_picker/frontend/build/styles.css
st_img_picker/frontend/package-lock.json
st_img_picker/frontend/package.json
st_img_picker/frontend/public/index.html
st_img_picker/frontend/public/styles.css
st_img_picker/frontend/src/index.tsx
st_img_picker/frontend/src/react-app-env.d.ts
st_img_picker/frontend/tsconfig.json
st_img_picker-1.0.2.dist-info/LICENSE
st_img_picker-1.0.2.dist-info/METADATA
st_img_picker-1.0.2.dist-info/WHEEL
st_img_picker-1.0.2.dist-info/RECORD
